disentanglement_lib/__init__.py
disentanglement_lib/disentanglement_lib.png
disentanglement_lib/config/__init__.py
disentanglement_lib/config/reproduce.py
disentanglement_lib/config/study.py
disentanglement_lib/config/abstract_reasoning_study_v1/__init__.py
disentanglement_lib/config/abstract_reasoning_study_v1/stage1/__init__.py
disentanglement_lib/config/abstract_reasoning_study_v1/stage1/sweep.py
disentanglement_lib/config/abstract_reasoning_study_v1/stage1/metric_configs/beta_vae_sklearn.gin
disentanglement_lib/config/abstract_reasoning_study_v1/stage1/metric_configs/dci.gin
disentanglement_lib/config/abstract_reasoning_study_v1/stage1/metric_configs/downstream_task_boosted_trees.gin
disentanglement_lib/config/abstract_reasoning_study_v1/stage1/metric_configs/downstream_task_logistic_regression.gin
disentanglement_lib/config/abstract_reasoning_study_v1/stage1/metric_configs/factor_vae_metric.gin
disentanglement_lib/config/abstract_reasoning_study_v1/stage1/metric_configs/mig.gin
disentanglement_lib/config/abstract_reasoning_study_v1/stage1/metric_configs/modularity_explicitness.gin
disentanglement_lib/config/abstract_reasoning_study_v1/stage1/metric_configs/sap_score.gin
disentanglement_lib/config/abstract_reasoning_study_v1/stage1/metric_configs/unsupervised.gin
disentanglement_lib/config/abstract_reasoning_study_v1/stage1/model_configs/shared.gin
disentanglement_lib/config/abstract_reasoning_study_v1/stage1/postprocess_configs/mean.gin
disentanglement_lib/config/abstract_reasoning_study_v1/stage1/postprocess_configs/sampled.gin
disentanglement_lib/config/abstract_reasoning_study_v1/stage2/example.gin
disentanglement_lib/config/fairness_study_v1/__init__.py
disentanglement_lib/config/fairness_study_v1/sweep.py
disentanglement_lib/config/fairness_study_v1/metric_configs/beta_vae_sklearn.gin
disentanglement_lib/config/fairness_study_v1/metric_configs/dci.gin
disentanglement_lib/config/fairness_study_v1/metric_configs/downstream_task_boosted_trees.gin
disentanglement_lib-1.5.dist-info/AUTHORS
disentanglement_lib-1.5.dist-info/LICENSE
disentanglement_lib-1.5.dist-info/METADATA
disentanglement_lib-1.5.dist-info/WHEEL
disentanglement_lib-1.5.dist-info/top_level.txt
disentanglement_lib-1.5.dist-info/RECORD
