Metadata-Version: 2.1
Name: disentanglement_lib
Version: 1.5
Summary: Library for research on disentangled representations.
Home-page: http://github.com/google-research/disentanglement_lib
Author: DisentanglementLib Authors
Author-email: no-reply@google.com
License: Apache 2.0
Keywords: tensorflow machine learning disentanglement learning
Platform: UNKNOWN
Classifier: Development Status :: 4 - Beta
Classifier: Intended Audience :: Developers
Classifier: Intended Audience :: Science/Research
Classifier: License :: OSI Approved :: Apache Software License
Classifier: Topic :: Scientific/Engineering :: Artificial Intelligence
Provides-Extra: tf
Provides-Extra: tf_gpu
